CONTRIBUTING.rst
HISTORY.rst
LICENSE
MANIFEST.in
README.rst
setup.cfg
setup.py
docs/Makefile
docs/api.rst
docs/conf.py
docs/contributing.rst
docs/flask_open_directory.base.rst
docs/flask_open_directory.model.rst
docs/flask_open_directory.query.rst
docs/flask_open_directory.rst
docs/history.rst
docs/index.rst
docs/installation.rst
docs/license.rst
docs/make.bat
docs/modules.rst
docs/readme.rst
docs/testing.rst
docs/usage.rst
docs/_build/html/_static/ajax-loader.gif
docs/_build/html/_static/comment-bright.png
docs/_build/html/_static/comment-close.png
docs/_build/html/_static/comment.png
docs/_build/html/_static/down-pressed.png
docs/_build/html/_static/down.png
docs/_build/html/_static/file.png
docs/_build/html/_static/minus.png
docs/_build/html/_static/plus.png
docs/_build/html/_static/up-pressed.png
docs/_build/html/_static/up.png
flask_open_directory/__init__.py
flask_open_directory/_compat.py
flask_open_directory/decorators.py
flask_open_directory/open_directory.py
flask_open_directory/utils.py
flask_open_directory.egg-info/PKG-INFO
flask_open_directory.egg-info/SOURCES.txt
flask_open_directory.egg-info/dependency_links.txt
flask_open_directory.egg-info/not-zip-safe
flask_open_directory.egg-info/requires.txt
flask_open_directory.egg-info/top_level.txt
tests/__init__.py
tests/conftest.py
tests/test_decorators.py
tests/test_open_directory_utils.py
tests/test_utils.py
tests/base/__init__.py
tests/base/test_base_open_directory.py
tests/base/test_open_directory_abc.py
tests/model/__init__.py
tests/model/test_model.py
tests/model/test_model_abc.py
tests/query/__init__.py
tests/query/conftest.py
tests/query/test_base_query.py
tests/query/test_query.py
tests/query/test_query_abc.py