Metadata-Version: 1.1
Name: flask-open-directory
Version: 0.1.1
Summary: MacOS OpenDirectory Authorization Middleware for Flask
Home-page: https://github.com/m-housh/flask_open_directory
Author: Michael Housh
Author-email: mhoush@houshhomeenergy.com
License: MIT license
Keywords: flask_open_directory
Platform: UNKNOWN
Classifier: Development Status :: 2 - Pre-Alpha
Classifier: Intended Audience :: Developers
Classifier: License :: OSI Approved :: MIT License
Classifier: Natural Language :: English
Classifier: Programming Language :: Python :: 3 :: Only
Classifier: Programming Language :: Python :: 3.5
Classifier: Programming Language :: Python :: 3.6
Classifier: Environment :: MacOS X
Classifier: Framework :: Flask
